cardpay/__init__.py
cardpay/api_client.py
cardpay/configuration.py
cardpay/rest.py
cardpay/api/__init__.py
cardpay/api/auth_api.py
cardpay/api/authentication_api.py
cardpay/api/card_info_api.py
cardpay/api/digital_onboarding_api.py
cardpay/api/invoices_api.py
cardpay/api/limits_api.py
cardpay/api/mobile_api.py
cardpay/api/payments_api.py
cardpay/api/payouts_api.py
cardpay/api/pix_account_details_api.py
cardpay/api/recurrings_api.py
cardpay/api/refunds_api.py
cardpay/api/reports_api_controller_api.py
cardpay/model/__init__.py
cardpay/model/account_details_request.py
cardpay/model/api_error.py
cardpay/model/api_tokens.py
cardpay/model/auth_data_request.py
cardpay/model/authentication_confirm3ds_request.py
cardpay/model/authentication_create_response.py
cardpay/model/authentication_customer.py
cardpay/model/authentication_data.py
cardpay/model/authentication_data_request.py
cardpay/model/authentication_data_response.py
cardpay/model/authentication_error.py
cardpay/model/authentication_patch_request.py
cardpay/model/authentication_update_response.py
cardpay/model/bad_request_error.py
cardpay/model/bank_card_payout_data.py
cardpay/model/billing_address.py
cardpay/model/browser_info.py
cardpay/model/card_info_request.py
cardpay/model/card_info_response.py
cardpay/model/change_subscription_status_claim_response.py
cardpay/model/changed_plan_data.py
cardpay/model/claim_response_subscription_data.py
cardpay/model/confirm3ds_request.py
cardpay/model/device.py
cardpay/model/digital_onboarding_request.py
cardpay/model/dispute_list.py
cardpay/model/dispute_response.py
cardpay/model/dispute_response_card.py
cardpay/model/dispute_response_card_account.py
cardpay/model/dispute_response_customer.py
cardpay/model/dispute_response_dispute_data.py
cardpay/model/dispute_response_merchant_order.py
cardpay/model/dispute_response_payment_data.py
cardpay/model/ewallet_account.py
cardpay/model/filing_recurring_data.py
cardpay/model/filing_request.py
cardpay-4.2.13.dist-info/LICENSE
cardpay-4.2.13.dist-info/METADATA
cardpay-4.2.13.dist-info/WHEEL
cardpay-4.2.13.dist-info/top_level.txt
cardpay-4.2.13.dist-info/RECORD
