Metadata-Version: 2.1
Name: cardpay
Version: 4.2.13
Summary: Unlimit APIv3 Python SDK
Home-page: https://github.com/cardpay/python-sdk-v3.git
Author-email: 
License: MIT
Project-URL: Source Code, https://github.com/cardpay/python-sdk-v3
Project-URL: Documentation, https://integration.unlimit.com/
Keywords: cardpay,APIv3,CardPay REST API
Platform: UNKNOWN
Classifier: Intended Audience :: Developers
Classifier: License :: OSI Approved :: MIT License
Classifier: Operating System :: OS Independent
Classifier: Programming Language :: Python :: 3
Classifier: Programming Language :: Python :: Implementation :: PyPy
Classifier: Topic :: Software Development :: Libraries :: Python Modules
Requires-Python: >=3
Requires-Dist: certifi (>=2019.11.28)
Requires-Dist: python-dateutil (>=2.8.0)
Requires-Dist: six (>=1.14.0)
Requires-Dist: urllib3 (>=1.25.8)
